setup.py
database_error_ex_forex_next3/__init__.py
database_error_ex_forex_next3/database_error_ex_forex_next3.py
database_error_ex_forex_next3.egg-info/PKG-INFO
database_error_ex_forex_next3.egg-info/SOURCES.txt
database_error_ex_forex_next3.egg-info/dependency_links.txt
database_error_ex_forex_next3.egg-info/not-zip-safe
database_error_ex_forex_next3.egg-info/top_level.txt