Metadata-Version: 1.0
Name: database-error-ex-forex-next3
Version: 1.1
Summary: database_error_ex_forex_next3
Home-page: UNKNOWN
Author: omid
Author-email: UNKNOWN
License: UNKNOWN
Platform: UNKNOWN
